ptf_fxw_m3/__init__.py
ptf_fxw_m3/M3_H3.pth
ptf_fxw_m3/ptf.py
ptf_fxw_m3-0.1.1.dist-info/METADATA
ptf_fxw_m3-0.1.1.dist-info/WHEEL
ptf_fxw_m3-0.1.1.dist-info/RECORD
