Metadata-Version: 2.1
Name: ptf-fxw-m3
Version: 0.1.1
Summary: 
Author: Wang Group
Author-email: Wang_Group_Cug@163.com
Requires-Python: >=3.10,<4.0
Classifier: Programming Language :: Python :: 3
Classifier: Programming Language :: Python :: 3.10
Classifier: Programming Language :: Python :: 3.11
Classifier: Programming Language :: Python :: 3.12
Requires-Dist: numpy (>=1.26.4,<2.0.0)
Requires-Dist: pandas (>=2.2.2,<3.0.0)
Requires-Dist: torch (>=2.3.1,<3.0.0)
